encoder/encoder.vhd
 library ieee;
use ieee.std_logic_1164.all;

entity encoder_8to3 is
    port(
        i : in  std_logic_vector(7 downto 0); -- one-hot inputs
        y : out std_logic_vector(2 downto 0)  -- encoded output
    );
end encoder_8to3;

architecture rtl of encoder_8to3 is
begin
    process(i)
    begin
        case i is
            when "00000001" => y <= "000";
            when "00000010" => y <= "001";
            when "00000100" => y <= "010";
            when "00001000" => y <= "011";
            when "00010000" => y <= "100";
            when "00100000" => y <= "101";
            when "01000000" => y <= "110";
            when "10000000" => y <= "111";
            when others      => y <= "000"; -- default / no input
        end case;
    end process;
end rtl;

encoder/tb_encoder.vhd
 library ieee;
use ieee.std_logic_1164.all;

entity tb_encoder_8to3 is
end tb_encoder_8to3;

architecture sim of tb_encoder_8to3 is
    signal i: std_logic_vector(7 downto 0) := (others => '0');
    signal y: std_logic_vector(2 downto 0);
begin
    uut: entity work.encoder_8to3
        port map(
            i => i,
            y => y
        );

    stim: process
    begin
        i <= "00000001"; wait for 50 ns;
        i <= "00000010"; wait for 50 ns;
        i <= "00000100"; wait for 50 ns;
        i <= "00001000"; wait for 50 ns;
        i <= "00010000"; wait for 50 ns;
        i <= "00100000"; wait for 50 ns;
        i <= "01000000"; wait for 50 ns;
        i <= "10000000"; wait for 50 ns;
        i <= "00000000"; wait for 50 ns;
        wait;
    end process;
end sim;

encoder/wave.vcd
$date
  Thu Dec 25 20:40:24 2025
$end
$version
  GHDL v0
$end
$timescale
  1 fs
$end
$scope module standard $end
$upscope $end
$scope module std_logic_1164 $end
$upscope $end
$scope module tb_encoder_8to3 $end
$var reg 8 ! i[7:0] $end
$var reg 3 " y[2:0] $end
$scope module uut $end
$var reg 8 # i[7:0] $end
$var reg 3 $ y[2:0] $end
$upscope $end
$upscope $end
$enddefinitions $end
#0
b00000001 !
b000 "
b00000001 #
b000 $
#50000000
b00000010 !
b001 "
b00000010 #
b001 $
#100000000
b00000100 !
b010 "
b00000100 #
b010 $
#150000000
b00001000 !
b011 "
b00001000 #
b011 $
#200000000
b00010000 !
b100 "
b00010000 #
b100 $
#250000000
b00100000 !
b101 "
b00100000 #
b101 $
#300000000
b01000000 !
b110 "
b01000000 #
b110 $
#350000000
b10000000 !
b111 "
b10000000 #
b111 $
#400000000
b00000000 !
b000 "
b00000000 #
b000 $
